{
  "id": "commands/page-save",
  "title": "Page Save - Session History Dump with Citations and Memory Management",
  "description": "Usage: /page-save",
  "source": "@site/docs/commands/page-save.md",
  "sourceDirName": "commands",
  "slug": "/commands/page-save",
  "permalink": "/cc-self-refer/docs/commands/page-save",
  "draft": false,
  "unlisted": false,
  "editUrl": "https://github.com/your-github-username/cc-self-refer/tree/main/docs/docs/commands/page-save.md",
  "tags": [],
  "version": "current",
  "frontMatter": {
    "id": "page-save",
    "title": "Page Save - Session History Dump with Citations and Memory Management",
    "sidebar_label": "/page-save"
  },
  "sidebar": "tutorialSidebar",
  "previous": {
    "title": "Overview",
    "permalink": "/cc-self-refer/docs/commands/overview"
  },
  "next": {
    "title": "/page-refer",
    "permalink": "/cc-self-refer/docs/commands/page-refer"
  }
}